arpakitlib/__init__.py
arpakitlib/ar_aiogram_as_tg_command_2_util.py
arpakitlib/ar_aiogram_as_tg_command_util.py
arpakitlib/ar_arpakit_project_template_util.py
arpakitlib/ar_arpakitlib_module_util.py
arpakitlib/ar_base64_util.py
arpakitlib/ar_base_http_api_client_util.py
arpakitlib/ar_base_worker_util.py
arpakitlib/ar_blank_util.py
arpakitlib/ar_cache_file_util.py
arpakitlib/ar_class_util.py
arpakitlib/ar_clone_pydantic_model_fields_util.py
arpakitlib/ar_datetime_util.py
arpakitlib/ar_dict_as_object.py
arpakitlib/ar_dict_util.py
arpakitlib/ar_encrypt_decrypt_util.py
arpakitlib/ar_enumeration_util.py
arpakitlib/ar_exception_util.py
arpakitlib/ar_file_storage_in_dir_util.py
arpakitlib/ar_file_util.py
arpakitlib/ar_func_util.py
arpakitlib/ar_generate_connection_url_util.py
arpakitlib/ar_generate_difficult_password_util.py
arpakitlib/ar_generate_simple_code_util.py
arpakitlib/ar_hash_util.py
arpakitlib/ar_http_request_util.py
arpakitlib/ar_include_aiogram_routers_from_dir_util.py
arpakitlib/ar_include_fastapi_routers_from_dir_util.py
arpakitlib/ar_ip_util.py
arpakitlib/ar_json_db_util.py
arpakitlib/ar_json_util.py
arpakitlib/ar_jwt_util.py
arpakitlib/ar_list_util.py
arpakitlib/ar_log_async_func_if_error_util.py
arpakitlib/ar_logging_util.py
arpakitlib/ar_make_zip_with_passwd.py
arpakitlib/ar_need_type_util.py
arpakitlib/ar_openai_api_client_util.py
arpakitlib/ar_parse_command_util.py
arpakitlib/ar_postgresql_util.py
arpakitlib/ar_pydantic_schema_from_sqlalchemy_model_util.py
arpakitlib/ar_raise_own_exception_if_exception_util.py
arpakitlib/ar_rat_func_util.py
arpakitlib/ar_really_validate_email_util.py
arpakitlib/ar_really_validate_url_util.py
arpakitlib/ar_retry_func_util.py
arpakitlib/ar_run_cmd_util.py
arpakitlib/ar_safe_func_util.py
arpakitlib/ar_settings_util.py
arpakitlib/ar_sleep_util.py
arpakitlib/ar_sqladmin_util.py
arpakitlib/ar_sqlalchemy_base_dbm_util.py
arpakitlib/ar_sqlalchemy_drop_check_constraints_util.py
arpakitlib-1.9.38.dist-info/METADATA
arpakitlib-1.9.38.dist-info/WHEEL
arpakitlib-1.9.38.dist-info/entry_points.txt
arpakitlib-1.9.38.dist-info/licenses/LICENSE
arpakitlib-1.9.38.dist-info/RECORD
