Metadata-Version: 2.4
Name: arpakitlib
Version: 1.9.38
Summary: arpakitlib
License-Expression: Apache-2.0
License-File: LICENSE
Keywords: arpakitlib,arpakit,arpakit-company,arpakitcompany,arpakit_company
Author: arpakit_company
Author-email: support@arpakit.com
Requires-Python: >=3.12.4,<4.0
Classifier: Development Status :: 5 - Production/Stable
Classifier: Intended Audience :: Developers
Classifier: License :: OSI Approved :: Apache Software License
Classifier: Programming Language :: Python
Classifier: Programming Language :: Python :: 3
Classifier: Programming Language :: Python :: 3.12
Classifier: Operating System :: OS Independent
Classifier: Topic :: Software Development :: Libraries
Requires-Dist: aio-pika (>=9.5.4,<10.0.0)
Requires-Dist: aiogram (>=3.22.0,<4.0.0)
Requires-Dist: aiohttp (>=3.11.16,<4.0.0)
Requires-Dist: aiohttp-socks (>=0.10.1,<0.11.0)
Requires-Dist: aiosmtplib (>=4.0.0,<5.0.0)
Requires-Dist: aiosqlite (>=0.21.0,<0.22.0)
Requires-Dist: alembic (>=1.14.1,<2.0.0)
Requires-Dist: asyncpg (>=0.30.0,<0.31.0)
Requires-Dist: asyncssh (>=2.21.1,<3.0.0)
Requires-Dist: bs4 (>=0.0.2,<0.0.3)
Requires-Dist: cachetools (>=5.5.1,<6.0.0)
Requires-Dist: celery (>=5.4.0,<6.0.0)
Requires-Dist: email-validator (>=2.2.0,<3.0.0)
Requires-Dist: emoji (>=2.14.1,<3.0.0)
Requires-Dist: fastapi (>=0.118.0,<0.119.0)
Requires-Dist: gunicorn (>=23.0.0,<24.0.0)
Requires-Dist: itsdangerous (>=2.2.0,<3.0.0)
Requires-Dist: markdown (>=3.7,<4.0)
Requires-Dist: openai (>=2.6.1,<3.0.0)
Requires-Dist: openpyxl (>=3.1.5,<4.0.0)
Requires-Dist: orjson (>=3.10.15,<4.0.0)
Requires-Dist: pandas (>=2.3.3,<3.0.0)
Requires-Dist: paramiko (>=4.0.0,<5.0.0)
Requires-Dist: pika (>=1.3.2,<2.0.0)
Requires-Dist: poetry (>=2.0.1,<3.0.0)
Requires-Dist: poetry-plugin-export (>=1.9.0)
Requires-Dist: psycopg2-binary (>=2.9.10,<3.0.0)
Requires-Dist: pulp (>=2.9.0,<3.0.0)
Requires-Dist: pydantic (>=2.10.5,<3.0.0)
Requires-Dist: pydantic-settings (>=2.7.1,<3.0.0)
Requires-Dist: pyjwt (>=2.10.1,<3.0.0)
Requires-Dist: pyminizip (>=0.2.6,<0.3.0)
Requires-Dist: pymongo (>=4.15.5,<5.0.0)
Requires-Dist: pytelegrambotapi (>=4.29.1,<5.0.0)
Requires-Dist: pytest (>=8.4.2,<9.0.0)
Requires-Dist: pytz (>=2024.2,<2025.0)
Requires-Dist: qrcode (>=8.2,<9.0)
Requires-Dist: rapidfuzz (>=3.14.1,<4.0.0)
Requires-Dist: redis (>=6.4.0,<7.0.0)
Requires-Dist: requests-ntlm (>=1.3.0,<2.0.0)
Requires-Dist: requests[socks] (>=2.32.3,<3.0.0)
Requires-Dist: sqladmin (>=0.21.0,<0.22.0)
Requires-Dist: sqlalchemy (>=2.0.37,<3.0.0)
Requires-Dist: twine (>=6.1.0,<7.0.0)
Requires-Dist: uvicorn (>=0.37.0,<0.38.0)
Requires-Dist: xlrd (>=2.0.1,<3.0.0)
Requires-Dist: xlsxwriter (>=3.2.5,<4.0.0)
Project-URL: Documentation, https://github.com/ARPAKIT-Company/arpakitlib
Project-URL: Homepage, https://github.com/ARPAKIT-Company/arpakitlib
Project-URL: arpakit_company_site, https://arpakit.com
Project-URL: arpakit_company_support_tg, https://t.me/arpakit_company_support
Project-URL: git_repository, https://github.com/ARPAKIT-Company/arpakitlib
Project-URL: telegram_channel, https://t.me/arpakitlib
